[
  {
    "id": 1,
    "company_id": 1,
    "type": "nova_poshta",
    "active": true
  },
  {
    "id": 2,
    "company_id": 1,
    "type": "ukrposhta",
    "active": true
  },
  {
    "id": 3,
    "company_id": 1,
    "type": "meest",
    "active": true
  },
  {
    "id": 4,
    "company_id": 1,
    "type": "pickup",
    "active": true
  },
  {
    "id": 5,
    "company_id": 2,
    "type": "nova_poshta",
    "active": true
  },
  {
    "id": 6,
    "company_id": 2,
    "type": "ukrposhta",
    "active": true
  },
  {
    "id": 7,
    "company_id": 2,
    "type": "meest",
    "active": true
  },
  {
    "id": 8,
    "company_id": 2,
    "type": "pickup",
    "active": true
  },
  {
    "id": 9,
    "company_id": 3,
    "type": "nova_poshta",
    "active": true
  },
  {
    "id": 10,
    "company_id": 3,
    "type": "ukrposhta",
    "active": true
  },
  {
    "id": 11,
    "company_id": 3,
    "type": "meest",
    "active": true
  },
  {
    "id": 12,
    "company_id": 3,
    "type": "pickup",
    "active": true
  },
  {
    "id": 13,
    "company_id": 4,
    "type": "nova_poshta",
    "active": true
  },
  {
    "id": 14,
    "company_id": 4,
    "type": "ukrposhta",
    "active": true
  },
  {
    "id": 15,
    "company_id": 4,
    "type": "meest",
    "active": true
  },
  {
    "id": 16,
    "company_id": 4,
    "type": "pickup",
    "active": true
  },
  {
    "id": 17,
    "company_id": 5,
    "type": "nova_poshta",
    "active": true
  },
  {
    "id": 18,
    "company_id": 5,
    "type": "ukrposhta",
    "active": true
  },
  {
    "id": 19,
    "company_id": 5,
    "type": "meest",
    "active": true
  },
  {
    "id": 20,
    "company_id": 5,
    "type": "pickup",
    "active": true
  },
  {
    "id": 21,
    "company_id": 6,
    "type": "nova_poshta",
    "active": true
  },
  {
    "id": 22,
    "company_id": 6,
    "type": "ukrposhta",
    "active": true
  },
  {
    "id": 23,
    "company_id": 6,
    "type": "meest",
    "active": true
  },
  {
    "id": 24,
    "company_id": 6,
    "type": "pickup",
    "active": true
  },
  {
    "id": 25,
    "company_id": 7,
    "type": "nova_poshta",
    "active": true
  },
  {
    "id": 26,
    "company_id": 7,
    "type": "ukrposhta",
    "active": true
  },
  {
    "id": 27,
    "company_id": 7,
    "type": "meest",
    "active": true
  },
  {
    "id": 28,
    "company_id": 7,
    "type": "pickup",
    "active": true
  },
  {
    "id": 29,
    "company_id": 8,
    "type": "nova_poshta",
    "active": true
  },
  {
    "id": 30,
    "company_id": 8,
    "type": "ukrposhta",
    "active": true
  },
  {
    "id": 31,
    "company_id": 8,
    "type": "meest",
    "active": true
  },
  {
    "id": 32,
    "company_id": 8,
    "type": "pickup",
    "active": true
  },
  {
    "id": 33,
    "company_id": 9,
    "type": "nova_poshta",
    "active": true
  },
  {
    "id": 34,
    "company_id": 9,
    "type": "ukrposhta",
    "active": true
  },
  {
    "id": 35,
    "company_id": 9,
    "type": "meest",
    "active": true
  },
  {
    "id": 36,
    "company_id": 9,
    "type": "pickup",
    "active": true
  },
  {
    "id": 37,
    "company_id": 10,
    "type": "nova_poshta",
    "active": true
  },
  {
    "id": 38,
    "company_id": 10,
    "type": "ukrposhta",
    "active": true
  },
  {
    "id": 39,
    "company_id": 10,
    "type": "meest",
    "active": true
  },
  {
    "id": 40,
    "company_id": 10,
    "type": "pickup",
    "active": true
  }
]
